pynotification/__init__.py
pynotification/mod.py
pynotification/pynotifier.py
pynotification/window.py
pynotification-0.1.3.dist-info/LICENSE
pynotification-0.1.3.dist-info/METADATA
pynotification-0.1.3.dist-info/WHEEL
pynotification-0.1.3.dist-info/top_level.txt
pynotification-0.1.3.dist-info/RECORD
