Metadata-Version: 2.1
Name: pynotification
Version: 0.1.3
Summary: Python module to trigger OS-agnostic notification/messagebox
Author-email: Vignesh Sivanandha Rao <svignesh1793@gmail.com>
License: MIT License
Project-URL: Homepage, https://github.com/thevickypedia/pynotification
Project-URL: Docs, https://thevickypedia.github.io/pynotification/
Project-URL: Source, https://github.com/thevickypedia/pynotification
Project-URL: Bug Tracker, https://github.com/thevickypedia/pynotification/issues
Project-URL: Release Notes, https://github.com/thevickypedia/pynotification/blob/main/release_notes.rst
Keywords: system,notification
Classifier: License :: OSI Approved :: MIT License
Classifier: Programming Language :: Python :: 3
Classifier: Development Status :: 5 - Production/Stable
Classifier: Operating System :: MacOS :: MacOS X
Classifier: Operating System :: Microsoft :: Windows
Classifier: Operating System :: POSIX :: Linux
Classifier: Topic :: Terminals :: Terminal Emulators/X Terminals
Requires-Python: >=3
License-File: LICENSE
Requires-Dist: pywin32 ; platform_system == "Windows"
Provides-Extra: dev
Requires-Dist: pytest ; extra == 'dev'
Requires-Dist: pre-commit ; extra == 'dev'
